dsr_model_sdk/__init__.py
dsr_model_sdk/dsr_sdk.py
dsr_model_sdk/jobs.py
dsr_model_sdk/logger.py
dsr_model_sdk/message.py
dsr_model_sdk/session.py
dsr_model_sdk/singleton.py
dsr_model_sdk/topics.py
dsr_model_sdk-0.0.15.dist-info/METADATA
dsr_model_sdk-0.0.15.dist-info/WHEEL
dsr_model_sdk-0.0.15.dist-info/licenses/LICENSE
dsr_model_sdk-0.0.15.dist-info/RECORD
