Metadata-Version: 2.1
Name: dsr-model-sdk
Version: 0.0.15
Summary: A agent helper support send data out the service
Project-URL: Homepage, https://the-hash.com
Project-URL: Bug Tracker, https://github.com/hashgroup/dsr-model-sdk/issues
Author-email: An Quach <an.quach@the-hash.com>
License-File: LICENSE
Classifier: License :: OSI Approved :: MIT License
Classifier: Operating System :: OS Independent
Classifier: Programming Language :: Python :: 3
Requires-Python: >=3.10
Requires-Dist: apscheduler==3.10.4
Requires-Dist: fastapi==0.103.2
Requires-Dist: requests==2.31.0
